{
  "id": "n8n-automation-templates-5000-template-1057-efd3423f75",
  "source": {
    "type": "github",
    "repository": "ritik-prog/n8n-automation-templates-5000",
    "repository_stars": 341,
    "path": "Templates based on paltforms/Slack/hr_1057_cron_email_to_slack.json",
    "url": "https://github.com/ritik-prog/n8n-automation-templates-5000/blob/main/Templates based on paltforms/Slack/hr_1057_cron_email_to_slack.json"
  },
  "name": "Template 1057",
  "description": "n8n workflow template from ritik-prog/n8n-automation-templates-5000: Template 1057",
  "category": "AI",
  "tags": [
    "Templates based on paltforms",
    "Slack",
    "cron",
    "email",
    "slack",
    "instagram",
    "cron Trigger",
    "template",
    "1057",
    "n8n",
    "workflow",
    "ritik"
  ],
  "task_keywords": [
    "template 1057",
    "cron",
    "email",
    "slack",
    "instagram",
    "cron trigger",
    "1057 n8n",
    "n8n workflow",
    "workflow template",
    "template ritik",
    "ritik prog",
    "prog n8n"
  ],
  "required_services": [
    "cron",
    "email",
    "slack",
    "instagram"
  ],
  "triggers": [
    "cron Trigger"
  ],
  "complexity": "simple",
  "workflow": {
    "name": "Template 1057",
    "nodes": [
      {
        "parameters": {
          "cronExpression": "*/12 * * * *"
        },
        "name": "Cron",
        "type": "n8n-nodes-base.cron",
        "typeVersion": 1,
        "position": [
          0,
          0
        ]
      },
      {
        "parameters": {},
        "name": "Set",
        "type": "n8n-nodes-base.set",
        "typeVersion": 1,
        "position": [
          300,
          0
        ]
      },
      {
        "parameters": {},
        "name": "Email",
        "type": "n8n-nodes-base.email",
        "typeVersion": 1,
        "position": [
          600,
          0
        ]
      },
      {
        "parameters": {},
        "name": "Slack",
        "type": "n8n-nodes-base.slack",
        "typeVersion": 1,
        "position": [
          900,
          0
        ]
      },
      {
        "parameters": {},
        "name": "Instagram",
        "type": "n8n-nodes-base.instagram",
        "typeVersion": 1,
        "position": [
          1200,
          0
        ]
      }
    ],
    "connections": {
      "Cron": {
        "main": [
          [
            {
              "node": "Set",
              "type": "main",
              "index": 0
            }
          ]
        ]
      },
      "Set": {
        "main": [
          [
            {
              "node": "Email",
              "type": "main",
              "index": 0
            }
          ]
        ]
      },
      "Email": {
        "main": [
          [
            {
              "node": "Slack",
              "type": "main",
              "index": 0
            }
          ]
        ]
      },
      "Slack": {
        "main": [
          [
            {
              "node": "Instagram",
              "type": "main",
              "index": 0
            }
          ]
        ]
      }
    },
    "active": false,
    "settings": {},
    "id": 1057
  }
}
