{
  "id": "n8n-automation-templates-5000-template-1322-c55acabf2f",
  "source": {
    "type": "github",
    "repository": "ritik-prog/n8n-automation-templates-5000",
    "repository_stars": 341,
    "path": "Templates based on paltforms/Misc/webhook_agents_1322_webhook_http_request_to_set.json",
    "url": "https://github.com/ritik-prog/n8n-automation-templates-5000/blob/main/Templates based on paltforms/Misc/webhook_agents_1322_webhook_http_request_to_set.json"
  },
  "name": "Template 1322",
  "description": "n8n workflow template from ritik-prog/n8n-automation-templates-5000: Template 1322",
  "category": "Productivity",
  "tags": [
    "Templates based on paltforms",
    "Misc",
    "httprequest",
    "webhook",
    "template",
    "1322",
    "n8n",
    "workflow",
    "ritik"
  ],
  "task_keywords": [
    "template 1322",
    "httprequest",
    "webhook",
    "1322 n8n",
    "n8n workflow",
    "workflow template",
    "template ritik",
    "ritik prog",
    "prog n8n",
    "n8n automation",
    "automation templates",
    "templates 5000"
  ],
  "required_services": [
    "httprequest"
  ],
  "triggers": [
    "webhook"
  ],
  "complexity": "simple",
  "workflow": {
    "name": "Template 1322",
    "nodes": [
      {
        "parameters": {
          "path": "auto-hook-1322",
          "httpMethod": "POST"
        },
        "name": "Webhook",
        "type": "n8n-nodes-base.webhook",
        "typeVersion": 1,
        "position": [
          0,
          0
        ]
      },
      {
        "parameters": {},
        "name": "Set",
        "type": "n8n-nodes-base.set",
        "typeVersion": 1,
        "position": [
          300,
          0
        ]
      },
      {
        "parameters": {},
        "name": "HTTP Request",
        "type": "n8n-nodes-base.httprequest",
        "typeVersion": 1,
        "position": [
          600,
          0
        ]
      },
      {
        "parameters": {},
        "name": "Set",
        "type": "n8n-nodes-base.set",
        "typeVersion": 1,
        "position": [
          900,
          0
        ]
      }
    ],
    "connections": {
      "Webhook": {
        "main": [
          [
            {
              "node": "Set",
              "type": "main",
              "index": 0
            }
          ]
        ]
      },
      "Set": {
        "main": [
          [
            {
              "node": "HTTP Request",
              "type": "main",
              "index": 0
            }
          ]
        ]
      },
      "HTTP Request": {
        "main": [
          [
            {
              "node": "Set",
              "type": "main",
              "index": 0
            }
          ]
        ]
      }
    },
    "active": false,
    "settings": {},
    "id": 1322
  }
}
