{
  "id": "n8n-automation-templates-5000-notify-on-slack-from-pagerduty-incident-and-send-to-pagerduty-13b9d97c0b",
  "source": {
    "type": "github",
    "repository": "ritik-prog/n8n-automation-templates-5000",
    "repository_stars": 341,
    "path": "n8n_2000_workflows/notify-on-slack-pagerduty-incident-pagerduty.json",
    "url": "https://github.com/ritik-prog/n8n-automation-templates-5000/blob/main/n8n_2000_workflows/notify-on-slack-pagerduty-incident-pagerduty.json"
  },
  "name": "Notify on slack from PagerDuty incident and send to PagerDuty",
  "description": "n8n workflow template from ritik-prog/n8n-automation-templates-5000: Notify on slack from PagerDuty incident and send to PagerDuty",
  "category": "Communication",
  "tags": [
    "n8n 2000 workflows",
    "slack",
    "webhook",
    "notify",
    "pagerduty",
    "incident",
    "send"
  ],
  "task_keywords": [
    "notify on slack from pagerduty incident and send to pagerduty",
    "slack",
    "send slack",
    "notify slack",
    "webhook",
    "slack pagerduty",
    "pagerduty incident",
    "incident send",
    "send pagerduty",
    "pagerduty n8n",
    "n8n workflow",
    "workflow template"
  ],
  "required_services": [
    "slack"
  ],
  "triggers": [
    "webhook"
  ],
  "complexity": "simple",
  "workflow": {
    "name": "Notify on slack from PagerDuty incident and send to PagerDuty",
    "nodes": [
      {
        "id": "trigger-pagerduty-incident",
        "name": "Incoming Trigger",
        "type": "n8n-nodes-base.webhook",
        "typeVersion": 1,
        "position": [
          -600,
          143200
        ],
        "parameters": {
          "httpMethod": "POST",
          "path": "notify-on-slack-from-pagerduty-incident-and-send-to-pagerduty",
          "responseCode": 200,
          "responseMode": "onReceived"
        }
      },
      {
        "id": "fetch-pagerduty-incident",
        "name": "Fetch data from PagerDuty incident",
        "type": "n8n-nodes-base.httpRequest",
        "typeVersion": 1,
        "position": [
          -300,
          143200
        ],
        "parameters": {
          "method": "GET",
          "url": "https://api.example.com/pagerduty-incident",
          "responseFormat": "json"
        }
      },
      {
        "id": "send-pagerduty",
        "name": "Send to PagerDuty",
        "type": "n8n-nodes-base.httpRequest",
        "typeVersion": 1,
        "position": [
          300,
          143200
        ],
        "parameters": {
          "method": "POST",
          "url": "https://api.example.com/pagerduty",
          "responseFormat": "json",
          "options": {}
        }
      },
      {
        "id": "error-handler-600-143200",
        "name": "Send Error to Slack",
        "type": "n8n-nodes-base.slack",
        "typeVersion": 1,
        "position": [
          600,
          143200
        ],
        "parameters": {
          "resource": "message",
          "operation": "post",
          "channel": "#automation-alerts",
          "text": "={{ $json.get('error_message', 'An error occurred') }}"
        }
      }
    ],
    "connections": {
      "Incoming Trigger": {
        "main": [
          [
            {
              "node": "Fetch data from PagerDuty incident",
              "type": "main",
              "index": 0
            }
          ]
        ]
      },
      "Fetch data from PagerDuty incident": {
        "main": [
          {
            "node": "Send to PagerDuty",
            "type": "main",
            "index": 0
          }
        ]
      },
      "Send to PagerDuty": {
        "main": [
          [
            {
              "node": "Send Error to Slack",
              "type": "main",
              "index": 0
            }
          ]
        ]
      }
    },
    "settings": {},
    "active": false
  }
}
