{
  "id": "n8n-automation-templates-5000-template-1880-d7358be889",
  "source": {
    "type": "github",
    "repository": "ritik-prog/n8n-automation-templates-5000",
    "repository_stars": 341,
    "path": "Templates based on paltforms/Google/government_&_non-profit_1880_webhook_google_sheets_to_email.json",
    "url": "https://github.com/ritik-prog/n8n-automation-templates-5000/blob/main/Templates based on paltforms/Google/government_&_non-profit_1880_webhook_google_sheets_to_email.json"
  },
  "name": "Template 1880",
  "description": "n8n workflow template from ritik-prog/n8n-automation-templates-5000: Template 1880",
  "category": "AI",
  "tags": [
    "Templates based on paltforms",
    "Google",
    "googlesheets",
    "email",
    "webhook",
    "template",
    "1880",
    "n8n",
    "workflow",
    "ritik"
  ],
  "task_keywords": [
    "template 1880",
    "googlesheets",
    "email",
    "webhook",
    "1880 n8n",
    "n8n workflow",
    "workflow template",
    "template ritik",
    "ritik prog",
    "prog n8n",
    "n8n automation",
    "automation templates"
  ],
  "required_services": [
    "googlesheets",
    "email"
  ],
  "triggers": [
    "webhook"
  ],
  "complexity": "simple",
  "workflow": {
    "name": "Template 1880",
    "nodes": [
      {
        "parameters": {
          "path": "auto-hook-1880",
          "httpMethod": "POST"
        },
        "name": "Webhook",
        "type": "n8n-nodes-base.webhook",
        "typeVersion": 1,
        "position": [
          0,
          0
        ]
      },
      {
        "parameters": {},
        "name": "Set",
        "type": "n8n-nodes-base.set",
        "typeVersion": 1,
        "position": [
          300,
          0
        ]
      },
      {
        "parameters": {},
        "name": "Google Sheets",
        "type": "n8n-nodes-base.googlesheets",
        "typeVersion": 1,
        "position": [
          600,
          0
        ]
      },
      {
        "parameters": {},
        "name": "Email",
        "type": "n8n-nodes-base.email",
        "typeVersion": 1,
        "position": [
          900,
          0
        ]
      }
    ],
    "connections": {
      "Webhook": {
        "main": [
          [
            {
              "node": "Set",
              "type": "main",
              "index": 0
            }
          ]
        ]
      },
      "Set": {
        "main": [
          [
            {
              "node": "Google Sheets",
              "type": "main",
              "index": 0
            }
          ]
        ]
      },
      "Google Sheets": {
        "main": [
          [
            {
              "node": "Email",
              "type": "main",
              "index": 0
            }
          ]
        ]
      }
    },
    "active": false,
    "settings": {},
    "id": 1880
  }
}
