{
  "id": "n8n-automation-templates-5000-generate-shipping-label-from-shopify-order-and-send-to-warehouse-system-e454075997",
  "source": {
    "type": "github",
    "repository": "ritik-prog/n8n-automation-templates-5000",
    "repository_stars": 341,
    "path": "n8n_2000_workflows/generate-shipping-label-shopify-order-warehouse-system.json",
    "url": "https://github.com/ritik-prog/n8n-automation-templates-5000/blob/main/n8n_2000_workflows/generate-shipping-label-shopify-order-warehouse-system.json"
  },
  "name": "Generate shipping label from Shopify order and send to Warehouse system",
  "description": "n8n workflow template from ritik-prog/n8n-automation-templates-5000: Generate shipping label from Shopify order and send to Warehouse system",
  "category": "Communication",
  "tags": [
    "n8n 2000 workflows",
    "slack",
    "webhook",
    "generate",
    "shipping",
    "label",
    "shopify",
    "order",
    "send"
  ],
  "task_keywords": [
    "generate shipping label from shopify order and send to warehouse system",
    "slack",
    "send slack",
    "webhook",
    "generate shipping",
    "shipping label",
    "label shopify",
    "shopify order",
    "order send",
    "send warehouse",
    "warehouse system",
    "system n8n"
  ],
  "required_services": [
    "slack"
  ],
  "triggers": [
    "webhook"
  ],
  "complexity": "simple",
  "workflow": {
    "name": "Generate shipping label from Shopify order and send to Warehouse system",
    "nodes": [
      {
        "id": "trigger-shopify-order",
        "name": "Incoming Trigger",
        "type": "n8n-nodes-base.webhook",
        "typeVersion": 1,
        "position": [
          -600,
          172700
        ],
        "parameters": {
          "httpMethod": "POST",
          "path": "generate-shipping-label-from-shopify-order-and-send-to-warehouse-system",
          "responseCode": 200,
          "responseMode": "onReceived"
        }
      },
      {
        "id": "fetch-shopify-order",
        "name": "Fetch data from Shopify order",
        "type": "n8n-nodes-base.httpRequest",
        "typeVersion": 1,
        "position": [
          -300,
          172700
        ],
        "parameters": {
          "method": "GET",
          "url": "https://api.example.com/shopify-order",
          "responseFormat": "json"
        }
      },
      {
        "id": "send-warehouse-system",
        "name": "Send to Warehouse system",
        "type": "n8n-nodes-base.httpRequest",
        "typeVersion": 1,
        "position": [
          300,
          172700
        ],
        "parameters": {
          "method": "POST",
          "url": "https://api.example.com/warehouse-system",
          "responseFormat": "json",
          "options": {}
        }
      },
      {
        "id": "error-handler-600-172700",
        "name": "Send Error to Slack",
        "type": "n8n-nodes-base.slack",
        "typeVersion": 1,
        "position": [
          600,
          172700
        ],
        "parameters": {
          "resource": "message",
          "operation": "post",
          "channel": "#automation-alerts",
          "text": "={{ $json.get('error_message', 'An error occurred') }}"
        }
      }
    ],
    "connections": {
      "Incoming Trigger": {
        "main": [
          [
            {
              "node": "Fetch data from Shopify order",
              "type": "main",
              "index": 0
            }
          ]
        ]
      },
      "Fetch data from Shopify order": {
        "main": [
          {
            "node": "Send to Warehouse system",
            "type": "main",
            "index": 0
          }
        ]
      },
      "Send to Warehouse system": {
        "main": [
          [
            {
              "node": "Send Error to Slack",
              "type": "main",
              "index": 0
            }
          ]
        ]
      }
    },
    "settings": {},
    "active": false
  }
}
